datasette_sqlite_vector/__init__.py
datasette_sqlite_vector-0.0.1a6.dist-info/METADATA
datasette_sqlite_vector-0.0.1a6.dist-info/WHEEL
datasette_sqlite_vector-0.0.1a6.dist-info/entry_points.txt
datasette_sqlite_vector-0.0.1a6.dist-info/top_level.txt
datasette_sqlite_vector-0.0.1a6.dist-info/RECORD
