Metadata-Version: 2.1
Name: datasette-sqlite-vector
Version: 0.0.1a6
Home-page: https://github.com/asg017/sqlite-vector
Author: Alex Garcia
License: MIT License, Apache License, Version 2.0
Project-URL: Issues, https://github.com/asg017/sqlite-vector/issues
Project-URL: CI, https://github.com/asg017/sqlite-vector/actions
Project-URL: Changelog, https://github.com/asg017/sqlite-vector/releases
Requires-Python: >=3.7
Requires-Dist: datasette
Requires-Dist: sqlite-vector
Provides-Extra: test
Requires-Dist: pytest ; extra == 'test'
